{
    "id": "2618JYP:27/02/2018",
    "type": "Route",
    "arrivalPoint": {
        "type": "Feature",
        "geometry": {
            "type": "Point",
            "coordinates": []
        }
    },
    "departurePoint": {
        "type": "Feature",
        "geometry": {
            "type": "Point",
            "coordinates": []
        }
    },
    "description": {
        "type": "String",
        "value": "",
        "metadata": {}
    },
    "longName": {
        "type": "String",
        "value": "",
        "metadata": {}
    },
    "realArrivalTimestamp": {
        "type": "String",
        "value": "2018-02-27T12:02:59+00:00",
        "metadata": {}
    },
    "realDepartureTimestamp": {
        "type": "String",
        "value": "2018-02-27T06:31:00+00:00",
        "metadata": {}
    },
    "realPath": {
        "type": "List",
        "value": [],
        "metadata": {}
    },
    "realStops": {
        "type": "List",
        "value": [
            {
                "refStop": "DepositPoint:B57941",
                "stopPoint": {
                    "type": "Feature",
                    "geometry": {
                        "type": "Point",
                        "coordinates": []
                    }
                },
                "arrivalTimestamp": "2018-02-27T12:02:59+00:00",
                "departureTimestamp": ""
            },
            {
                "refStop": "DepositPoint:B56E76",
                "stopPoint": {
                    "type": "Feature",
                    "geometry": {
                        "type": "Point",
                        "coordinates": []
                    }
                },
                "arrivalTimestamp": "2018-02-27T09:40:00+00:00",
                "departureTimestamp": ""
            },
            {
                "refStop": "DepositPoint:B58FF8",
                "stopPoint": {
                    "type": "Feature",
                    "geometry": {
                        "type": "Point",
                        "coordinates": []
                    }
                },
                "arrivalTimestamp": "2018-02-27T09:38:00+00:00",
                "departureTimestamp": ""
            },
            {
                "refStop": "DepositPoint:B57EE5",
                "stopPoint": {
                    "type": "Feature",
                    "geometry": {
                        "type": "Point",
                        "coordinates": []
                    }
                },
                "arrivalTimestamp": "2018-02-27T09:36:00+00:00",
                "departureTimestamp": ""
            },
            {
                "refStop": "DepositPoint:B5435F",
                "stopPoint": {
                    "type": "Feature",
                    "geometry": {
                        "type": "Point",
                        "coordinates": []
                    }
                },
                "arrivalTimestamp": "2018-02-27T09:33:59+00:00",
                "departureTimestamp": ""
            },
            {
                "refStop": "DepositPoint:ZAMIP",
                "stopPoint": {
                    "type": "Feature",
                    "geometry": {
                        "type": "Point",
                        "coordinates": []
                    }
                },
                "arrivalTimestamp": "2018-02-27T09:31:59+00:00",
                "departureTimestamp": ""
            },
            {
                "refStop": "DepositPoint:B54B2A",
                "stopPoint": {
                    "type": "Feature",
                    "geometry": {
                        "type": "Point",
                        "coordinates": []
                    }
                },
                "arrivalTimestamp": "2018-02-27T09:31:00+00:00",
                "departureTimestamp": ""
            },
            {
                "refStop": "DepositPoint:ZAMIP",
                "stopPoint": {
                    "type": "Feature",
                    "geometry": {
                        "type": "Point",
                        "coordinates": []
                    }
                },
                "arrivalTimestamp": "2018-02-27T09:26:00+00:00",
                "departureTimestamp": ""
            },
            {
                "refStop": "DepositPoint:8F072A",
                "stopPoint": {
                    "type": "Feature",
                    "geometry": {
                        "type": "Point",
                        "coordinates": []
                    }
                },
                "arrivalTimestamp": "2018-02-27T09:22:59+00:00",
                "departureTimestamp": ""
            },
            {
                "refStop": "DepositPoint:B54E04",
                "stopPoint": {
                    "type": "Feature",
                    "geometry": {
                        "type": "Point",
                        "coordinates": []
                    }
                },
                "arrivalTimestamp": "2018-02-27T09:20:59+00:00",
                "departureTimestamp": ""
            },
            {
                "refStop": "DepositPoint:B548B5",
                "stopPoint": {
                    "type": "Feature",
                    "geometry": {
                        "type": "Point",
                        "coordinates": []
                    }
                },
                "arrivalTimestamp": "2018-02-27T09:18:59+00:00",
                "departureTimestamp": ""
            },
            {
                "refStop": "DepositPoint:ZAMIP",
                "stopPoint": {
                    "type": "Feature",
                    "geometry": {
                        "type": "Point",
                        "coordinates": []
                    }
                },
                "arrivalTimestamp": "2018-02-27T09:15:59+00:00",
                "departureTimestamp": ""
            },
            {
                "refStop": "DepositPoint:B54A4C",
                "stopPoint": {
                    "type": "Feature",
                    "geometry": {
                        "type": "Point",
                        "coordinates": []
                    }
                },
                "arrivalTimestamp": "2018-02-27T09:13:59+00:00",
                "departureTimestamp": ""
            },
            {
                "refStop": "DepositPoint:8EFB09",
                "stopPoint": {
                    "type": "Feature",
                    "geometry": {
                        "type": "Point",
                        "coordinates": []
                    }
                },
                "arrivalTimestamp": "2018-02-27T09:08:00+00:00",
                "departureTimestamp": ""
            },
            {
                "refStop": "DepositPoint:ZAMIP",
                "stopPoint": {
                    "type": "Feature",
                    "geometry": {
                        "type": "Point",
                        "coordinates": []
                    }
                },
                "arrivalTimestamp": "2018-02-27T09:08:00+00:00",
                "departureTimestamp": ""
            },
            {
                "refStop": "DepositPoint:8EE598",
                "stopPoint": {
                    "type": "Feature",
                    "geometry": {
                        "type": "Point",
                        "coordinates": []
                    }
                },
                "arrivalTimestamp": "2018-02-27T08:48:00+00:00",
                "departureTimestamp": ""
            },
            {
                "refStop": "DepositPoint:F09D7D",
                "stopPoint": {
                    "type": "Feature",
                    "geometry": {
                        "type": "Point",
                        "coordinates": []
                    }
                },
                "arrivalTimestamp": "2018-02-27T07:41:59+00:00",
                "departureTimestamp": ""
            },
            {
                "refStop": "DepositPoint:F07DE1",
                "stopPoint": {
                    "type": "Feature",
                    "geometry": {
                        "type": "Point",
                        "coordinates": []
                    }
                },
                "arrivalTimestamp": "2018-02-27T07:38:59+00:00",
                "departureTimestamp": ""
            },
            {
                "refStop": "DepositPoint:F08A9C",
                "stopPoint": {
                    "type": "Feature",
                    "geometry": {
                        "type": "Point",
                        "coordinates": []
                    }
                },
                "arrivalTimestamp": "2018-02-27T07:36:59+00:00",
                "departureTimestamp": ""
            },
            {
                "refStop": "DepositPoint:F0B38D",
                "stopPoint": {
                    "type": "Feature",
                    "geometry": {
                        "type": "Point",
                        "coordinates": []
                    }
                },
                "arrivalTimestamp": "2018-02-27T07:36:00+00:00",
                "departureTimestamp": ""
            },
            {
                "refStop": "DepositPoint:F08EAE",
                "stopPoint": {
                    "type": "Feature",
                    "geometry": {
                        "type": "Point",
                        "coordinates": []
                    }
                },
                "arrivalTimestamp": "2018-02-27T07:30:59+00:00",
                "departureTimestamp": ""
            },
            {
                "refStop": "DepositPoint:F0BA64",
                "stopPoint": {
                    "type": "Feature",
                    "geometry": {
                        "type": "Point",
                        "coordinates": []
                    }
                },
                "arrivalTimestamp": "2018-02-27T07:27:59+00:00",
                "departureTimestamp": ""
            },
            {
                "refStop": "DepositPoint:F0C5CA",
                "stopPoint": {
                    "type": "Feature",
                    "geometry": {
                        "type": "Point",
                        "coordinates": []
                    }
                },
                "arrivalTimestamp": "2018-02-27T07:25:00+00:00",
                "departureTimestamp": ""
            },
            {
                "refStop": "DepositPoint:F0CD1F",
                "stopPoint": {
                    "type": "Feature",
                    "geometry": {
                        "type": "Point",
                        "coordinates": []
                    }
                },
                "arrivalTimestamp": "2018-02-27T07:20:00+00:00",
                "departureTimestamp": ""
            },
            {
                "refStop": "DepositPoint:F099C0",
                "stopPoint": {
                    "type": "Feature",
                    "geometry": {
                        "type": "Point",
                        "coordinates": []
                    }
                },
                "arrivalTimestamp": "2018-02-27T07:18:59+00:00",
                "departureTimestamp": ""
            },
            {
                "refStop": "DepositPoint:F0897C",
                "stopPoint": {
                    "type": "Feature",
                    "geometry": {
                        "type": "Point",
                        "coordinates": []
                    }
                },
                "arrivalTimestamp": "2018-02-27T07:16:00+00:00",
                "departureTimestamp": ""
            },
            {
                "refStop": "DepositPoint:F08E0A",
                "stopPoint": {
                    "type": "Feature",
                    "geometry": {
                        "type": "Point",
                        "coordinates": []
                    }
                },
                "arrivalTimestamp": "2018-02-27T07:14:59+00:00",
                "departureTimestamp": ""
            },
            {
                "refStop": "DepositPoint:F09F84",
                "stopPoint": {
                    "type": "Feature",
                    "geometry": {
                        "type": "Point",
                        "coordinates": []
                    }
                },
                "arrivalTimestamp": "2018-02-27T07:14:00+00:00",
                "departureTimestamp": ""
            },
            {
                "refStop": "DepositPoint:F099AF",
                "stopPoint": {
                    "type": "Feature",
                    "geometry": {
                        "type": "Point",
                        "coordinates": []
                    }
                },
                "arrivalTimestamp": "2018-02-27T07:12:59+00:00",
                "departureTimestamp": ""
            },
            {
                "refStop": "DepositPoint:F09BDD",
                "stopPoint": {
                    "type": "Feature",
                    "geometry": {
                        "type": "Point",
                        "coordinates": []
                    }
                },
                "arrivalTimestamp": "2018-02-27T06:53:00+00:00",
                "departureTimestamp": ""
            },
            {
                "refStop": "DepositPoint:F08B3F",
                "stopPoint": {
                    "type": "Feature",
                    "geometry": {
                        "type": "Point",
                        "coordinates": []
                    }
                },
                "arrivalTimestamp": "2018-02-27T06:51:00+00:00",
                "departureTimestamp": ""
            },
            {
                "refStop": "DepositPoint:8EC5C3",
                "stopPoint": {
                    "type": "Feature",
                    "geometry": {
                        "type": "Point",
                        "coordinates": []
                    }
                },
                "arrivalTimestamp": "2018-02-27T06:47:00+00:00",
                "departureTimestamp": ""
            },
            {
                "refStop": "DepositPoint:8BA38D",
                "stopPoint": {
                    "type": "Feature",
                    "geometry": {
                        "type": "Point",
                        "coordinates": []
                    }
                },
                "arrivalTimestamp": "2018-02-27T06:44:00+00:00",
                "departureTimestamp": ""
            },
            {
                "refStop": "DepositPoint:8EC348",
                "stopPoint": {
                    "type": "Feature",
                    "geometry": {
                        "type": "Point",
                        "coordinates": []
                    }
                },
                "arrivalTimestamp": "2018-02-27T06:44:00+00:00",
                "departureTimestamp": ""
            },
            {
                "refStop": "DepositPoint:8EB3CD",
                "stopPoint": {
                    "type": "Feature",
                    "geometry": {
                        "type": "Point",
                        "coordinates": []
                    }
                },
                "arrivalTimestamp": "2018-02-27T06:42:59+00:00",
                "departureTimestamp": ""
            },
            {
                "refStop": "DepositPoint:8BA2E5",
                "stopPoint": {
                    "type": "Feature",
                    "geometry": {
                        "type": "Point",
                        "coordinates": []
                    }
                },
                "arrivalTimestamp": "2018-02-27T06:40:00+00:00",
                "departureTimestamp": ""
            },
            {
                "refStop": "DepositPoint:8EF462",
                "stopPoint": {
                    "type": "Feature",
                    "geometry": {
                        "type": "Point",
                        "coordinates": []
                    }
                },
                "arrivalTimestamp": "2018-02-27T06:38:59+00:00",
                "departureTimestamp": ""
            },
            {
                "refStop": "DepositPoint:8BA51B",
                "stopPoint": {
                    "type": "Feature",
                    "geometry": {
                        "type": "Point",
                        "coordinates": []
                    }
                },
                "arrivalTimestamp": "2018-02-27T06:33:00+00:00",
                "departureTimestamp": ""
            },
            {
                "refStop": "DepositPoint:8BB8EA",
                "stopPoint": {
                    "type": "Feature",
                    "geometry": {
                        "type": "Point",
                        "coordinates": []
                    }
                },
                "arrivalTimestamp": "2018-02-27T06:31:00+00:00",
                "departureTimestamp": ""
            }
        ],
        "metadata": {}
    },
    "refAssignedVehicle": {
        "type": "String",
        "value": "Vehicle:2618JYP",
        "metadata": {}
    },
    "refScheduledVehicle": {
        "type": "String",
        "value": "",
        "metadata": {}
    },
    "scheduledArrivalTimestamp": {
        "type": "String",
        "value": "",
        "metadata": {}
    },
    "scheduledDepartureTimestamp": {
        "type": "String",
        "value": "",
        "metadata": {}
    },
    "scheduledPath": {
        "type": "List",
        "value": [],
        "metadata": {}
    },
    "scheduledStops": {
        "type": "List",
        "value": [],
        "metadata": {}
    },
    "shortName": {
        "type": "String",
        "value": "",
        "metadata": {}
    },
    "vehicleType": {
        "type": "String",
        "value": "",
        "metadata": {}
    }
}